[
  {
    "ContainingType": "RoomlyAPI.Controllers.EquipamentoController",
    "Method": "Get",
    "RelativePath": "api/Equipamento",
    "HttpMethod": "GET",
    "IsController": true,
    "Order": 0,
    "Parameters": [],
    "ReturnTypes": []
  },
  {
    "ContainingType": "RoomlyAPI.Controllers.EquipamentoController",
    "Method": "Post",
    "RelativePath": "api/Equipamento",
    "HttpMethod": "POST",
    "IsController": true,
    "Order": 0,
    "Parameters": [
      {
        "Name": "equipamento",
        "Type": "RoomlyAPI.Domains.Equipamentos",
        "IsRequired": true
      }
    ],
    "ReturnTypes": []
  },
  {
    "ContainingType": "RoomlyAPI.Controllers.EquipamentoController",
    "Method": "GetById",
    "RelativePath": "api/Equipamento/{id}",
    "HttpMethod": "GET",
    "IsController": true,
    "Order": 0,
    "Parameters": [
      {
        "Name": "id",
        "Type": "System.Guid",
        "IsRequired": true
      }
    ],
    "ReturnTypes": []
  },
  {
    "ContainingType": "RoomlyAPI.Controllers.ReservaController",
    "Method": "Get",
    "RelativePath": "api/Reserva",
    "HttpMethod": "GET",
    "IsController": true,
    "Order": 0,
    "Parameters": [],
    "ReturnTypes": []
  },
  {
    "ContainingType": "RoomlyAPI.Controllers.ReservaController",
    "Method": "Post",
    "RelativePath": "api/Reserva",
    "HttpMethod": "POST",
    "IsController": true,
    "Order": 0,
    "Parameters": [
      {
        "Name": "reserva",
        "Type": "RoomlyAPI.Domains.Reserva",
        "IsRequired": true
      }
    ],
    "ReturnTypes": []
  },
  {
    "ContainingType": "RoomlyAPI.Controllers.ReservaController",
    "Method": "GetById",
    "RelativePath": "api/Reserva/{id}",
    "HttpMethod": "GET",
    "IsController": true,
    "Order": 0,
    "Parameters": [
      {
        "Name": "id",
        "Type": "System.Guid",
        "IsRequired": true
      }
    ],
    "ReturnTypes": []
  },
  {
    "ContainingType": "RoomlyAPI.Controllers.SalaController",
    "Method": "Get",
    "RelativePath": "api/Sala",
    "HttpMethod": "GET",
    "IsController": true,
    "Order": 0,
    "Parameters": [],
    "ReturnTypes": []
  },
  {
    "ContainingType": "RoomlyAPI.Controllers.SalaController",
    "Method": "Post",
    "RelativePath": "api/Sala",
    "HttpMethod": "POST",
    "IsController": true,
    "Order": 0,
    "Parameters": [
      {
        "Name": "sala",
        "Type": "RoomlyAPI.Domains.Sala",
        "IsRequired": true
      }
    ],
    "ReturnTypes": []
  },
  {
    "ContainingType": "RoomlyAPI.Controllers.SalaController",
    "Method": "GetById",
    "RelativePath": "api/Sala/{id}",
    "HttpMethod": "GET",
    "IsController": true,
    "Order": 0,
    "Parameters": [
      {
        "Name": "id",
        "Type": "System.Guid",
        "IsRequired": true
      }
    ],
    "ReturnTypes": []
  },
  {
    "ContainingType": "RoomlyAPI.Controllers.TiposUsuarioController",
    "Method": "Get",
    "RelativePath": "api/TiposUsuario",
    "HttpMethod": "GET",
    "IsController": true,
    "Order": 0,
    "Parameters": [],
    "ReturnTypes": []
  },
  {
    "ContainingType": "RoomlyAPI.Controllers.TiposUsuarioController",
    "Method": "Post",
    "RelativePath": "api/TiposUsuario",
    "HttpMethod": "POST",
    "IsController": true,
    "Order": 0,
    "Parameters": [
      {
        "Name": "tiposUsuario",
        "Type": "RoomlyAPI.Domains.TiposUsuario",
        "IsRequired": true
      }
    ],
    "ReturnTypes": []
  },
  {
    "ContainingType": "RoomlyAPI.Controllers.TiposUsuarioController",
    "Method": "GetById",
    "RelativePath": "api/TiposUsuario/{id}",
    "HttpMethod": "GET",
    "IsController": true,
    "Order": 0,
    "Parameters": [
      {
        "Name": "id",
        "Type": "System.Guid",
        "IsRequired": true
      }
    ],
    "ReturnTypes": []
  },
  {
    "ContainingType": "RoomlyAPI.Controllers.UsuarioController",
    "Method": "Post",
    "RelativePath": "api/Usuario",
    "HttpMethod": "POST",
    "IsController": true,
    "Order": 0,
    "Parameters": [
      {
        "Name": "usuario",
        "Type": "RoomlyAPI.Domains.Usuario",
        "IsRequired": true
      }
    ],
    "ReturnTypes": []
  },
  {
    "ContainingType": "RoomlyAPI.Controllers.UsuarioController",
    "Method": "Get",
    "RelativePath": "api/Usuario",
    "HttpMethod": "GET",
    "IsController": true,
    "Order": 0,
    "Parameters": [],
    "ReturnTypes": []
  }
]